{
  "sections": {
    "main": {
      "type": "main-page",
      "disabled": true,
      "settings": {
        "padding_top": 28,
        "padding_bottom": 28
      }
    },
    "165042188498a35df5": {
      "type": "rich-text",
      "blocks": {
        "165042188404ebf07c-0": {
          "type": "heading",
          "settings": {
            "heading": "About Us",
            "heading_size": "h1"
          }
        },
        "165042188404ebf07c-1": {
          "type": "text",
          "settings": {
            "text": "<p>Why you should start buy furnitures from Stockie?<\/p>"
          }
        }
      },
      "block_order": [
        "165042188404ebf07c-0",
        "165042188404ebf07c-1"
      ],
      "settings": {
        "color_scheme": "background-1",
        "full_width": true,
        "padding_top": 40,
        "padding_bottom": 0
      }
    },
    "16504214890790b912": {
      "type": "multicolumn",
      "blocks": {
        "16504214895fa4c874-0": {
          "type": "column",
          "settings": {
            "title": "",
            "text": "<p>We create unique high-quality furniture<\/p>",
            "link_label": "",
            "link": ""
          }
        },
        "16504214895fa4c874-1": {
          "type": "column",
          "settings": {
            "title": "",
            "text": "<p>Natoque cras habitant dictum faucibus gravida ultrices litora facilisi senectus vehicula ligula montes sem, leo primis phasellus suscipit integer sapien himenaeos est aptent non fusce congue. Sapien cubilia orci blandit lacus curabitur et erat <\/p><p>maximus fames conubia egestas ultricies nullam adipiscing eros nostra mauris tristique aliquam netus. Adipiscing fusce velit lacinia  <\/p>",
            "link_label": "",
            "link": ""
          }
        }
      },
      "block_order": [
        "16504214895fa4c874-0",
        "16504214895fa4c874-1"
      ],
      "settings": {
        "title": "",
        "heading_size": "h1",
        "image_width": "full",
        "image_ratio": "adapt",
        "columns_desktop": 2,
        "column_alignment": "left",
        "background_style": "none",
        "button_label": "",
        "button_link": "",
        "color_scheme": "background-1",
        "columns_mobile": "1",
        "swipe_on_mobile": false,
        "padding_top": 36,
        "padding_bottom": 0
      }
    },
    "16505299335342f093": {
      "type": "multicolumn",
      "blocks": {
        "1650529933c5fcb7ed-0": {
          "type": "column",
          "settings": {
            "image": "shopify:\/\/shop_images\/logoipsum-logo-45.png",
            "title": "",
            "text": "",
            "link_label": "",
            "link": ""
          }
        },
        "1650529933c5fcb7ed-1": {
          "type": "column",
          "settings": {
            "image": "shopify:\/\/shop_images\/logoipsum-logo-43.png",
            "title": "",
            "text": "",
            "link_label": "",
            "link": ""
          }
        },
        "1650529933c5fcb7ed-2": {
          "type": "column",
          "settings": {
            "image": "shopify:\/\/shop_images\/logoipsum-logo-28.png",
            "title": "",
            "text": "",
            "link_label": "",
            "link": ""
          }
        },
        "df2a3ce4-f3fd-4631-ad1c-a6c158b34269": {
          "type": "column",
          "settings": {
            "image": "shopify:\/\/shop_images\/logoipsum-logo-40.png",
            "title": "",
            "text": "",
            "link_label": "",
            "link": ""
          }
        },
        "6612a079-847d-4ff9-a8c6-0577bb858f41": {
          "type": "column",
          "settings": {
            "image": "shopify:\/\/shop_images\/logoipsum-logo-26.png",
            "title": "",
            "text": "",
            "link_label": "",
            "link": ""
          }
        },
        "e11d8109-340f-486d-9f85-30d5421e90ee": {
          "type": "column",
          "settings": {
            "image": "shopify:\/\/shop_images\/logoipsum-logo-17.png",
            "title": "",
            "text": "",
            "link_label": "",
            "link": ""
          }
        }
      },
      "block_order": [
        "1650529933c5fcb7ed-0",
        "1650529933c5fcb7ed-1",
        "1650529933c5fcb7ed-2",
        "df2a3ce4-f3fd-4631-ad1c-a6c158b34269",
        "6612a079-847d-4ff9-a8c6-0577bb858f41",
        "e11d8109-340f-486d-9f85-30d5421e90ee"
      ],
      "settings": {
        "title": "",
        "heading_size": "h1",
        "image_width": "full",
        "image_ratio": "adapt",
        "columns_desktop": 6,
        "column_alignment": "left",
        "background_style": "none",
        "button_label": "",
        "button_link": "",
        "color_scheme": "background-1",
        "columns_mobile": "2",
        "swipe_on_mobile": false,
        "padding_top": 16,
        "padding_bottom": 28
      }
    },
    "1650539048094ad08f": {
      "type": "testimonial-carousel",
      "settings": {
      }
    }
  },
  "order": [
    "main",
    "165042188498a35df5",
    "16504214890790b912",
    "16505299335342f093",
    "1650539048094ad08f"
  ]
}